praktikum/__init__.py
praktikum/basic_electronic.py
praktikum/oscillator_copitts.py
praktikum/oscillator_hartley.py
elfrad_itb-1.0.0.dist-info/LICENSE
elfrad_itb-1.0.0.dist-info/METADATA
elfrad_itb-1.0.0.dist-info/WHEEL
elfrad_itb-1.0.0.dist-info/top_level.txt
elfrad_itb-1.0.0.dist-info/RECORD
